assignment_desk/__init__.py
assignment_desk/admin.py
assignment_desk/apps.py
assignment_desk/checks.py
assignment_desk/field_renderers.py
assignment_desk/forms.py
assignment_desk/mixins.py
assignment_desk/models.py
assignment_desk/signals.py
assignment_desk/tests.py
assignment_desk/urls.py
assignment_desk/utils.py
assignment_desk/views.py
assignment_desk/migrations/0001_initial.py
assignment_desk/migrations/0002_week_role_type.py
assignment_desk/migrations/0003_auto_20180615_1551.py
assignment_desk/migrations/0004_auto_20180809_1432.py
assignment_desk/migrations/0005_auto_20180814_1438.py
assignment_desk/migrations/0006_auto_20180906_1203.py
assignment_desk/migrations/__init__.py
assignment_desk/static/assignment_desk/css/main.css
assignment_desk/static/assignment_desk/css/main.css.map
assignment_desk/static/assignment_desk/js/sitewide-scripts.js
assignment_desk/static/assignment_desk/js/sitewide-scripts.js.map
assignment_desk/static/assignment_desk/js/week.create.js
assignment_desk/static/assignment_desk/js/week.create.js.map
assignment_desk/static/assignment_desk/js/week.delete.js
assignment_desk/static/assignment_desk/js/week.delete.js.map
assignment_desk/static/assignment_desk/js/week.detail.js
assignment_desk/static/assignment_desk/js/week.detail.js.map
assignment_desk/static/assignment_desk/js/week.edit.js
assignment_desk/static/assignment_desk/js/week.edit.js.map
assignment_desk/static/assignment_desk/js/week.list.js
assignment_desk/static/assignment_desk/js/week.list.js.map
assignment_desk/staticapp/gulp/index.js
assignment_desk/staticapp/gulp/tasks/browserify.js
assignment_desk/staticapp/gulp/tasks/jsify.js
assignment_desk/staticapp/gulp/tasks/scss.js
assignment_desk/staticapp/gulp/tasks/server.js
assignment_desk/staticapp/gulp/tasks/watchify.js
assignment_desk/staticapp/js/.eslintrc.json
assignment_desk/staticapp/js/sitewide-scripts.js
assignment_desk/staticapp/js/week.create.js
assignment_desk/staticapp/js/week.delete.js
django_assignment_desk-0.1.10.dist-info/LICENSE
django_assignment_desk-0.1.10.dist-info/METADATA
django_assignment_desk-0.1.10.dist-info/WHEEL
django_assignment_desk-0.1.10.dist-info/top_level.txt
django_assignment_desk-0.1.10.dist-info/RECORD
