Metadata-Version: 2.1
Name: django-assignment-desk
Version: 0.1.10
Summary: A simple app to manage newsroom staff assignments.
Home-page: https://github.com/DallasMorningNews/django-assignment-desk/
Author: Alma Washington and Allan James Vestal, The Dallas Morning News
Author-email: newsapps@dallasnews.com
License: AGPLv3
Download-URL: https://github.com/DallasMorningNews/django-assignment-desk/archive/0.1.10.tar.gz
Platform: UNKNOWN
Classifier: Environment :: Web Environment
Classifier: Framework :: Django
Classifier: Intended Audience :: Developers
Classifier: License :: OSI Approved :: GNU Affero General Public License v3
Classifier: Operating System :: OS Independent
Classifier: Programming Language :: Python
Classifier: Programming Language :: Python :: 2
Classifier: Programming Language :: Python :: 2.6
Classifier: Programming Language :: Python :: 2.7
Classifier: Programming Language :: Python :: 3
Classifier: Programming Language :: Python :: 3.4
Classifier: Programming Language :: Python :: 3.5
Classifier: Topic :: Internet :: WWW/HTTP
Classifier: Topic :: Internet :: WWW/HTTP :: Dynamic Content
Requires-Dist: Django (>=1.11.0)
Requires-Dist: django-bootstrap3 (~=9.0.0)
Requires-Dist: django-colorfield (~=0.1.10)
Requires-Dist: django-editorial-staff (~=0.8.0)
